pycodemarker/__init__.py
pycodemarker/codemarker.py
pycodemarker/log_helper.py
pycodemarker/publisher.py
pycodemarker-0.0.4.dist-info/LICENSE.txt
pycodemarker-0.0.4.dist-info/METADATA
pycodemarker-0.0.4.dist-info/WHEEL
pycodemarker-0.0.4.dist-info/top_level.txt
pycodemarker-0.0.4.dist-info/RECORD
