Metadata-Version: 2.1
Name: pycodemarker
Version: 0.0.4
Summary: Code Marker Library from Doctor Droid to instrumenting product metrics
Author: Dipesh Mittal
Author-email: dipeshmittal14@gmail.com
License: MIT
Classifier: Programming Language :: Python :: 3
Classifier: License :: OSI Approved :: MIT License
Classifier: Operating System :: OS Independent
Requires-Python: >=3.6
License-File: LICENSE.txt
